uglyorange/__init__.py
uglyorange/cli/__init__.py
uglyorange/cli/rc.py
uglyorange/install/__init__.py
uglyorange/install/app.py
uglyorange/install/endlessh.py
uglyorange/install/monitor.py
uglyorange/install/nftest.py
uglyorange/install/python.py
uglyorange/install/supervisor.py
uglyorange/install/swap.py
uglyorange/install/timezone.py
uglyorange/install/trojan.py
uglyorange/install/ttyd.py
uglyorange/install/types.py
uglyorange/install/utils.py
uglyorange/network.py
uglyorange/sys.py
uglyorange/utils.py
uglyorange-0.1.14.dist-info/METADATA
uglyorange-0.1.14.dist-info/WHEEL
uglyorange-0.1.14.dist-info/entry_points.txt
uglyorange-0.1.14.dist-info/RECORD
